snakeskin/__init__.py
snakeskin/config.py
snakeskin/connect.py
snakeskin/constants.py
snakeskin/crypto.py
snakeskin/errors.py
snakeskin/events.py
snakeskin/factories.py
snakeskin/gateway.py
snakeskin/operations.py
snakeskin/transact.py
snakeskin/tx_flow.py
snakeskin/_hfc/__init__.py
snakeskin/_hfc/crypto.py
snakeskin/models/__init__.py
snakeskin/models/_decoded.py
snakeskin/models/block.py
snakeskin/models/gateway.py
snakeskin/models/transaction.py
snakeskin/protos/__init__.py
snakeskin/protos/common/__init__.py
snakeskin/protos/common/collection_pb2.py
snakeskin/protos/common/collection_pb2_grpc.py
snakeskin/protos/common/common_pb2.py
snakeskin/protos/common/common_pb2_grpc.py
snakeskin/protos/common/configtx_pb2.py
snakeskin/protos/common/configtx_pb2_grpc.py
snakeskin/protos/common/configuration_pb2.py
snakeskin/protos/common/configuration_pb2_grpc.py
snakeskin/protos/common/ledger_pb2.py
snakeskin/protos/common/ledger_pb2_grpc.py
snakeskin/protos/common/policies_pb2.py
snakeskin/protos/common/policies_pb2_grpc.py
snakeskin/protos/discovery/__init__.py
snakeskin/protos/discovery/protocol_pb2.py
snakeskin/protos/discovery/protocol_pb2_grpc.py
snakeskin/protos/gossip/__init__.py
snakeskin/protos/gossip/message_pb2.py
snakeskin/protos/gossip/message_pb2_grpc.py
snakeskin/protos/idemix/__init__.py
snakeskin/protos/idemix/idemix_pb2.py
snakeskin/protos/idemix/idemix_pb2_grpc.py
snakeskin/protos/ledger/__init__.py
snakeskin/protos/ledger/queryresult/__init__.py
snakeskin/protos/ledger/queryresult/kv_query_result_pb2.py
snakeskin/protos/ledger/queryresult/kv_query_result_pb2_grpc.py
snakeskin/protos/ledger/rwset/__init__.py
snakeskin/protos/ledger/rwset/rwset_pb2.py
snakeskin/protos/ledger/rwset/rwset_pb2_grpc.py
snakeskin/protos/ledger/rwset/kvrwset/__init__.py
snakeskin/protos/ledger/rwset/kvrwset/kv_rwset_pb2.py
snakeskin/protos/ledger/rwset/kvrwset/kv_rwset_pb2_grpc.py
snakeskin/protos/msp/__init__.py
snakeskin/protos/msp/identities_pb2.py
snakeskin_fabric-0.1.1.dist-info/LICENSE
snakeskin_fabric-0.1.1.dist-info/METADATA
snakeskin_fabric-0.1.1.dist-info/WHEEL
snakeskin_fabric-0.1.1.dist-info/top_level.txt
snakeskin_fabric-0.1.1.dist-info/RECORD
