Metadata-Version: 2.1
Name: snakeskin-fabric
Version: 0.1.1
Summary: An unofficial Python SDK for Hyperledger Fabric
Home-page: https://github.com/healthverity/snakeskin-fabric/
Author: HealthVerity
License: Apache License v2.0
Download-URL: https://github.com/healthverity/snakeskin-fabric/
Keywords: Hyperledger Fabric,SDK,Snakeskin
Platform: any
Requires-Dist: aiogrpc (>=1.6)
Requires-Dist: cryptography (>=2.7)
Requires-Dist: hkdf (>=0.0.3)
Requires-Dist: pycryptodomex (>=3.8.2)
Requires-Dist: pysha3 (>=1.0.2)
Requires-Dist: requests (>=2.22.0)
Requires-Dist: six (>=1.12.0)
Requires-Dist: protobuf (>=3.9.0)
Requires-Dist: pyyaml (>=5.1)
Requires-Dist: dacite (>=1.0.2)
